[
    {
        "image_url": "https://scontent-ort2-1.cdninstagram.com/v/t51.2885-15/e35/93796000_888872314907446_1972594445444618766_n.jpg?_nc_ht=scontent-ort2-1.cdninstagram.com&_nc_cat=110&_nc_ohc=F43VOusgu1MAX_338Gi&oh=19439ca62624e52361e44c017d38d216&oe=5EBDAD64",
        "url": "https://instagram.com/p/B_AtVhHKovM",
        "timestamp": 1586974258
    },
    {
        "image_url": "https://scontent-ort2-1.cdninstagram.com/v/t51.2885-15/fr/e15/s1080x1080/79510938_203696093999624_5089913124917528900_n.jpg?_nc_ht=scontent-ort2-1.cdninstagram.com&_nc_cat=108&_nc_ohc=uf_Yqon7wTsAX_nH57r&oh=596d7a2bbe2c315e60d87e478bde44a3&oe=5EE4A77E",
        "url": "https://instagram.com/p/B6VU4q6n61P",
        "timestamp": 1576928619
    },
    {
        "image_url": "https://scontent-ort2-1.cdninstagram.com/v/t51.2885-15/e35/s1080x1080/65010566_2326823544238833_2496084392212298948_n.jpg?_nc_ht=scontent-ort2-1.cdninstagram.com&_nc_cat=109&_nc_ohc=5nzesS7qEfcAX8sgRnj&oh=330ed5a157acaf2e280e8fc203d0737c&oe=5EE46F3F",
        "url": "https://instagram.com/p/BzLwW9PI24v",
        "timestamp": 1561575093
    },
    {
        "image_url": "https://scontent-ort2-1.cdninstagram.com/v/t51.2885-15/fr/e15/s1080x1080/62031203_1899337886834382_6425219355827957052_n.jpg?_nc_ht=scontent-ort2-1.cdninstagram.com&_nc_cat=106&_nc_ohc=cxB7imeVZ4kAX9qdfgN&oh=4d68477c726541f2d4bba3c2e04bd4a6&oe=5EE59D27",
        "url": "https://instagram.com/p/BytIFn7Hblx",
        "timestamp": 1560547347
    },
    {
        "image_url": "https://scontent-ort2-1.cdninstagram.com/v/t51.2885-15/e35/42443774_2098003533798867_2130869469333843943_n.jpg?_nc_ht=scontent-ort2-1.cdninstagram.com&_nc_cat=103&_nc_ohc=MujkTzdWWUkAX_MEU_p&oh=f5e52fb0e040edcac4005011dcfa270b&oe=5EE49C34",
        "url": "https://instagram.com/p/Bow1GCKHrdY",
        "timestamp": 1539196770
    },
    {
        "image_url": "https://scontent-ort2-1.cdninstagram.com/v/t51.2885-15/e35/40392455_276564596518761_4732640518868662710_n.jpg?_nc_ht=scontent-ort2-1.cdninstagram.com&_nc_cat=109&_nc_ohc=QCP-hUt4qFEAX9NyrrK&oh=594b97921af30307d2254529a47f5230&oe=5EE6B4B4",
        "url": "https://instagram.com/p/Bnt2_2SH5HN",
        "timestamp": 1536949621
    },
    {
        "image_url": "https://scontent-ort2-1.cdninstagram.com/v/t51.2885-15/fr/e15/s1080x1080/40395061_351006985440395_894541048083120128_n.jpg?_nc_ht=scontent-ort2-1.cdninstagram.com&_nc_cat=111&_nc_ohc=agEOT5pUj4QAX9WvM1b&oh=948657451bfab38f5b185b8b213e1430&oe=5EE441C7",
        "url": "https://instagram.com/p/BnMDrVMnvEB",
        "timestamp": 1535815418
    },
    {
        "image_url": "https://scontent-ort2-1.cdninstagram.com/v/t51.2885-15/e35/39082072_315509399200533_9007827793139990528_n.jpg?_nc_ht=scontent-ort2-1.cdninstagram.com&_nc_cat=109&_nc_ohc=EJolui32Br4AX9IG1mr&oh=66014a40f25b15deed3ed4fcfea4a8d6&oe=5EE47308",
        "url": "https://instagram.com/p/Bm5LwIzH3VO",
        "timestamp": 1535182117
    },
    {
        "image_url": "https://scontent-ort2-1.cdninstagram.com/v/t51.2885-15/e15/35616467_167359027460690_320140690375835648_n.jpg?_nc_ht=scontent-ort2-1.cdninstagram.com&_nc_cat=102&_nc_ohc=vWX-8E3FmH4AX-8i5a4&oh=172aa60129141a9b26044e9f452d43ad&oe=5EBDCEF2",
        "url": "https://instagram.com/p/BkxvlmNH0lx",
        "timestamp": 1530637684
    },
    {
        "image_url": "https://scontent-ort2-1.cdninstagram.com/v/t51.2885-15/e35/35540252_203775040246373_9077088989806067712_n.jpg?_nc_ht=scontent-ort2-1.cdninstagram.com&_nc_cat=105&_nc_ohc=7xI4Um8Vgv0AX-1I_Pd&oh=9787b5bb8c15f1e469b00727758cdddb&oe=5EE46FB4",
        "url": "https://instagram.com/p/BkN7pWtglSd",
        "timestamp": 1529435865
    },
    {
        "image_url": "https://scontent-ort2-1.cdninstagram.com/v/t51.2885-15/fr/e15/s1080x1080/29401614_539213049793999_4896521463449780224_n.jpg?_nc_ht=scontent-ort2-1.cdninstagram.com&_nc_cat=107&_nc_ohc=Glz3OuoH2QcAX9az6z_&oh=facf86cd500f589bfcc5876ca2efaea2&oe=5EE539D7",
        "url": "https://instagram.com/p/BhCnfYyF5fu",
        "timestamp": 1522613748
    },
    {
        "image_url": "https://scontent-ort2-1.cdninstagram.com/v/t51.2885-15/e15/27892585_2002240326709937_1152520264467087360_n.jpg?_nc_ht=scontent-ort2-1.cdninstagram.com&_nc_cat=105&_nc_ohc=quaFI2KFaD4AX9Yaoeu&oh=aa49ad34e59d7a4f381ae86cba1c8455&oe=5EE63EC2",
        "url": "https://instagram.com/p/BfWgjAIlR10",
        "timestamp": 1518986229
    }
]